microllama/Dockerfile
microllama/__init__.py
microllama/example.source.json
microllama/index.html
microllama-0.4.10.dist-info/entry_points.txt
microllama-0.4.10.dist-info/LICENSE
microllama-0.4.10.dist-info/WHEEL
microllama-0.4.10.dist-info/METADATA
microllama-0.4.10.dist-info/RECORD
