Metadata-Version: 2.1
Name: microllama
Version: 0.4.10
Summary: The smallest possible LLM API
Author-email: Tom Dyson <tom@torchbox.com>
Classifier: License :: OSI Approved :: MIT License
Requires-Dist: langchain
Requires-Dist: tiktoken
Requires-Dist: faiss-cpu
Requires-Dist: openai
Requires-Dist: fastapi
Requires-Dist: uvicorn[standard]
Requires-Dist: sse-starlette
Requires-Dist: typer
Project-URL: Home, https://github.com/tomdyson/microllama
